triecli.py
cli/__init__.py
cli/trie_nathaniel.py
trie_nathaniel-1.0.0.dist-info/LICENSE.txt
trie_nathaniel-1.0.0.dist-info/METADATA
trie_nathaniel-1.0.0.dist-info/WHEEL
trie_nathaniel-1.0.0.dist-info/entry_points.txt
trie_nathaniel-1.0.0.dist-info/top_level.txt
trie_nathaniel-1.0.0.dist-info/RECORD
