Metadata-Version: 2.1
Name: trie-nathaniel
Version: 1.0.0
Summary: Calls commands to the trie server that can modify its state
Home-page: https://github.com/Nathaniel-github/CombinedServerClientRepo
Author: Nathaniel Thomas
Author-email: catchnate+pypi@gmail.com
License: MIT
Platform: UNKNOWN
Classifier: Development Status :: 6 - Mature
Classifier: Environment :: Console
Classifier: License :: OSI Approved :: MIT License
Classifier: Natural Language :: English
Classifier: Operating System :: OS Independent
Classifier: Programming Language :: Python :: 3.8
Requires-Python: >=3.6, < 3.10
Requires-Dist: inquirer (~=2.7.0)
Requires-Dist: click (~=8.0.3)
